elysia/__init__.py
elysia/elysia.py
elysia-1.1.1.dist-info/LICENSE.md
elysia-1.1.1.dist-info/METADATA
elysia-1.1.1.dist-info/WHEEL
elysia-1.1.1.dist-info/RECORD
