Metadata-Version: 2.1
Name: elysia
Version: 1.1.1
Summary: An alternative API for creating attrs fields
Home-page: https://github.com/celsiusnarhwal/elysia
License: MIT
Keywords: attrs,class,attribute
Author: celsius narhwal
Author-email: hello@celsiusnarhwal.dev
Requires-Python: >=3.7,<4.0
Classifier: License :: OSI Approved :: MIT License
Classifier: Programming Language :: Python :: 3
Classifier: Programming Language :: Python :: 3.7
Classifier: Programming Language :: Python :: 3.8
Classifier: Programming Language :: Python :: 3.9
Classifier: Programming Language :: Python :: 3.10
Classifier: Programming Language :: Python :: 3.11
Requires-Dist: attrs (>=22.2.0,<23.0.0)
Requires-Dist: pydantic (>=1.10.5,<2.0.0)
